{
  "status": 0,
  "result": [
    {
      "createdById": "0051I000000npTMQAY",
      "createdByName": "Peerless Admin",
      "createdDate": "2018-03-29T20:35:33.000Z",
      "fileName": "triggers/ServiceAppointmentTrigger.trigger",
      "fullName": "ServiceAppointmentTrigger",
      "id": "01q1I000001cx9zQAA",
      "lastModifiedById": "00517000004PBL2AAO",
      "lastModifiedByName": "zakir hossain",
      "lastModifiedDate": "2020-01-28T09:48:22.000Z",
      "manageableState": "unmanaged",
      "type": "ApexTrigger"
    },
    {
      "createdById": "0051I000000cjG8QAI",
      "createdByName": "FSL",
      "createdDate": "2019-10-13T03:20:44.000Z",
      "fileName": "triggers/FSL__TR066_ServiceObjective.trigger",
      "fullName": "FSL__TR066_ServiceObjective",
      "id": "01q17000000QFgbAAG",
      "lastModifiedById": "0051I000000cjG8QAI",
      "lastModifiedByName": "FSL",
      "lastModifiedDate": "2019-10-13T03:20:44.000Z",
      "manageableState": "installed",
      "namespacePrefix": "FSL",
      "type": "ApexTrigger"
    },
    {
      "createdById": "0051I000000npTMQAY",
      "createdByName": "Peerless Admin",
      "createdDate": "2019-04-08T14:42:02.000Z",
      "fileName": "triggers/rh2__PS_Describe.trigger",
      "fullName": "rh2__PS_Describe",
      "id": "01q1I000001ZItSQAW",
      "lastModifiedById": "0051I000000npTMQAY",
      "lastModifiedByName": "Peerless Admin",
      "lastModifiedDate": "2019-04-08T14:42:02.000Z",
      "manageableState": "installed",
      "namespacePrefix": "rh2",
      "type": "ApexTrigger"
    },
    {
      "createdById": "0051I000000cjG8QAI",
      "createdByName": "FSL",
      "createdDate": "2018-10-13T07:13:16.000Z",
      "fileName": "triggers/FSL__TR030_GanttPalette_AfterInsert.trigger",
      "fullName": "FSL__TR030_GanttPalette_AfterInsert",
      "id": "01q1I000001IaakQAC",
      "lastModifiedById": "0051I000000cjG8QAI",
      "lastModifiedByName": "FSL",
      "lastModifiedDate": "2019-10-13T03:20:44.000Z",
      "manageableState": "installed",
      "namespacePrefix": "FSL",
      "type": "ApexTrigger"
    },
    {
      "createdById": "0051I000000cWGjQAM",
      "createdByName": "Dean White",
      "createdDate": "2017-09-22T04:06:34.000Z",
      "fileName": "triggers/FSL__TR024_SkillRequirement_BeforeUpdate.trigger",
      "fullName": "FSL__TR024_SkillRequirement_BeforeUpdate",
      "id": "01q1I000000ocmHQAQ",
      "lastModifiedById": "0051I000000cjG8QAI",
      "lastModifiedByName": "FSL",
      "lastModifiedDate": "2019-10-13T03:20:43.000Z",
      "manageableState": "installed",
      "namespacePrefix": "FSL",
      "type": "ApexTrigger"
    },
    {
      "createdById": "0051I000000cjG8QAI",
      "createdByName": "FSL",
      "createdDate": "2018-10-13T07:13:16.000Z",
      "fileName": "triggers/FSL__TR030_GanttPalette_BeforeInsertUpdate.trigger",
      "fullName": "FSL__TR030_GanttPalette_BeforeInsertUpdate",
      "id": "01q1I000001IaamQAC",
      "lastModifiedById": "0051I000000cjG8QAI",
      "lastModifiedByName": "FSL",
      "lastModifiedDate": "2019-10-13T03:20:44.000Z",
      "manageableState": "installed",
      "namespacePrefix": "FSL",
      "type": "ApexTrigger"
    },
    {
      "createdById": "0051I000000cWGjQAM",
      "createdByName": "Dean White",
      "createdDate": "2017-09-22T04:06:33.000Z",
      "fileName": "triggers/FSL__TR010_SchedulingPolicy_AfterInsert.trigger",
      "fullName": "FSL__TR010_SchedulingPolicy_AfterInsert",
      "id": "01q1I000000ocluQAA",
      "lastModifiedById": "0051I000000cjG8QAI",
      "lastModifiedByName": "FSL",
      "lastModifiedDate": "2019-10-13T03:20:42.000Z",
      "manageableState": "installed",
      "namespacePrefix": "FSL",
      "type": "ApexTrigger"
    },
    {
      "createdById": "0051I000002SKdRQAW",
      "createdByName": "MapAnything",
      "createdDate": "2019-02-24T17:25:19.000Z",
      "fileName": "triggers/sma__MATerritoryGeometry.trigger",
      "fullName": "sma__MATerritoryGeometry",
      "id": "01q1I000001ZHS0QAO",
      "lastModifiedById": "0051I000002SKdRQAW",
      "lastModifiedByName": "MapAnything",
      "lastModifiedDate": "2019-11-15T06:31:43.000Z",
      "manageableState": "installed",
      "namespacePrefix": "sma",
      "type": "ApexTrigger"
    },
    {
      "createdById": "0051I000000npTMQAY",
      "createdByName": "Peerless Admin",
      "createdDate": "2019-06-20T04:07:32.000Z",
      "fileName": "triggers/OpportunityHDTrim.trigger",
      "fullName": "OpportunityHDTrim",
      "id": "01q17000000BGtTAAW",
      "lastModifiedById": "0051I000000npTMQAY",
      "lastModifiedByName": "Peerless Admin",
      "lastModifiedDate": "2019-06-20T15:13:48.000Z",
      "manageableState": "unmanaged",
      "type": "ApexTrigger"
    },
    {
      "createdById": "0051I000000cWGjQAM",
      "createdByName": "Dean White",
      "createdDate": "2017-09-22T04:06:33.000Z",
      "fileName": "triggers/FSL__TR007_ResourceAbsence_AfterUpdate.trigger",
      "fullName": "FSL__TR007_ResourceAbsence_AfterUpdate",
      "id": "01q1I000000oclnQAA",
      "lastModifiedById": "0051I000000cjG8QAI",
      "lastModifiedByName": "FSL",
      "lastModifiedDate": "2019-10-13T03:20:42.000Z",
      "manageableState": "installed",
      "namespacePrefix": "FSL",
      "type": "ApexTrigger"
    },
    {
      "createdById": "0051I000000cWGjQAM",
      "createdByName": "Dean White",
      "createdDate": "2017-09-22T04:06:34.000Z",
      "fileName": "triggers/FSL__TR021_AssignedResource_AfterUpdate.trigger",
      "fullName": "FSL__TR021_AssignedResource_AfterUpdate",
      "id": "01q1I000000ocm4QAA",
      "lastModifiedById": "0051I000000cjG8QAI",
      "lastModifiedByName": "FSL",
      "lastModifiedDate": "2019-10-13T03:20:43.000Z",
      "manageableState": "installed",
      "namespacePrefix": "FSL",
      "type": "ApexTrigger"
    },
    {
      "createdById": "0051I000000npTMQAY",
      "createdByName": "Peerless Admin",
      "createdDate": "2018-07-20T22:09:31.000Z",
      "fileName": "triggers/sma__SavedQuery.trigger",
      "fullName": "sma__SavedQuery",
      "id": "01q1I000000C9lEQAS",
      "lastModifiedById": "0051I000002SKdRQAW",
      "lastModifiedByName": "MapAnything",
      "lastModifiedDate": "2019-11-15T06:31:43.000Z",
      "manageableState": "installed",
      "namespacePrefix": "sma",
      "type": "ApexTrigger"
    },
    {
      "createdById": "0051I000000npTMQAY",
      "createdByName": "Peerless Admin",
      "createdDate": "2019-04-08T14:42:02.000Z",
      "fileName": "triggers/rh2__PS_Queue.trigger",
      "fullName": "rh2__PS_Queue",
      "id": "01q1I000001ZItVQAW",
      "lastModifiedById": "0051I000000npTMQAY",
      "lastModifiedByName": "Peerless Admin",
      "lastModifiedDate": "2019-04-08T14:42:02.000Z",
      "manageableState": "installed",
      "namespacePrefix": "rh2",
      "type": "ApexTrigger"
    },
    {
      "createdById": "0051I000000cWGjQAM",
      "createdByName": "Dean White",
      "createdDate": "2017-09-22T04:06:33.000Z",
      "fileName": "triggers/FSL__SchedulingPolicyWorkRule_BeforeDelete.trigger",
      "fullName": "FSL__SchedulingPolicyWorkRule_BeforeDelete",
      "id": "01q1I000000oclTQAQ",
      "lastModifiedById": "0051I000000cjG8QAI",
      "lastModifiedByName": "FSL",
      "lastModifiedDate": "2019-10-13T03:20:40.000Z",
      "manageableState": "installed",
      "namespacePrefix": "FSL",
      "type": "ApexTrigger"
    },
    {
      "createdById": "0051I000000npTMQAY",
      "createdByName": "Peerless Admin",
      "createdDate": "2018-07-19T15:39:28.000Z",
      "fileName": "triggers/TaskTrigger.trigger",
      "fullName": "TaskTrigger",
      "id": "01q1I000000C9inQAC",
      "lastModifiedById": "0051I000000npTMQAY",
      "lastModifiedByName": "Peerless Admin",
      "lastModifiedDate": "2019-10-29T00:45:32.000Z",
      "manageableState": "unmanaged",
      "type": "ApexTrigger"
    },
    {
      "createdById": "0051I000000cWGjQAM",
      "createdByName": "Dean White",
      "createdDate": "2017-09-22T04:06:33.000Z",
      "fileName": "triggers/FSL__TR021_AssignedResource_AfterDelete.trigger",
      "fullName": "FSL__TR021_AssignedResource_AfterDelete",
      "id": "01q1I000000ocm2QAA",
      "lastModifiedById": "0051I000000cjG8QAI",
      "lastModifiedByName": "FSL",
      "lastModifiedDate": "2019-10-13T03:20:43.000Z",
      "manageableState": "installed",
      "namespacePrefix": "FSL",
      "type": "ApexTrigger"
    },
    {
      "createdById": "0051I000000npTMQAY",
      "createdByName": "Peerless Admin",
      "createdDate": "2018-02-20T16:45:09.000Z",
      "fileName": "triggers/dsfs__DocuSignChatterDocuSignStatus.trigger",
      "fullName": "dsfs__DocuSignChatterDocuSignStatus",
      "id": "01q1I000000SqfJQAS",
      "lastModifiedById": "0051I000000npTMQAY",
      "lastModifiedByName": "Peerless Admin",
      "lastModifiedDate": "2018-02-20T16:45:09.000Z",
      "manageableState": "installed",
      "namespacePrefix": "dsfs",
      "type": "ApexTrigger"
    },
    {
      "createdById": "0051I000000npTMQAY",
      "createdByName": "Peerless Admin",
      "createdDate": "2019-08-22T01:46:08.000Z",
      "fileName": "triggers/AccountTrigger.trigger",
      "fullName": "AccountTrigger",
      "id": "01q17000000BzWzAAK",
      "lastModifiedById": "0051I000000npTMQAY",
      "lastModifiedByName": "Peerless Admin",
      "lastModifiedDate": "2019-08-22T02:53:27.000Z",
      "manageableState": "unmanaged",
      "type": "ApexTrigger"
    },
    {
      "createdById": "0051I000000cWGjQAM",
      "createdByName": "Dean White",
      "createdDate": "2017-09-22T04:06:33.000Z",
      "fileName": "triggers/FSL__TR012_CapacityAfterUpdate.trigger",
      "fullName": "FSL__TR012_CapacityAfterUpdate",
      "id": "01q1I000000oclwQAA",
      "lastModifiedById": "0051I000000cjG8QAI",
      "lastModifiedByName": "FSL",
      "lastModifiedDate": "2019-10-13T03:20:42.000Z",
      "manageableState": "installed",
      "namespacePrefix": "FSL",
      "type": "ApexTrigger"
    },
    {
      "createdById": "0051I000000cWGjQAM",
      "createdByName": "Dean White",
      "createdDate": "2017-09-22T04:06:33.000Z",
      "fileName": "triggers/FSL__TR021_AssignedResource_AfterInsert.trigger",
      "fullName": "FSL__TR021_AssignedResource_AfterInsert",
      "id": "01q1I000000ocm3QAA",
      "lastModifiedById": "0051I000000cjG8QAI",
      "lastModifiedByName": "FSL",
      "lastModifiedDate": "2019-10-13T03:20:43.000Z",
      "manageableState": "installed",
      "namespacePrefix": "FSL",
      "type": "ApexTrigger"
    },
    {
      "createdById": "0051I000000cWGjQAM",
      "createdByName": "Dean White",
      "createdDate": "2017-09-22T04:06:33.000Z",
      "fileName": "triggers/FSL__TR001_Service_AfterInsert.trigger",
      "fullName": "FSL__TR001_Service_AfterInsert",
      "id": "01q1I000000oclUQAQ",
      "lastModifiedById": "0051I000000cjG8QAI",
      "lastModifiedByName": "FSL",
      "lastModifiedDate": "2019-10-13T03:20:41.000Z",
      "manageableState": "installed",
      "namespacePrefix": "FSL",
      "type": "ApexTrigger"
    },
    {
      "createdById": "0051I000000cWGjQAM",
      "createdByName": "Dean White",
      "createdDate": "2017-09-22T04:06:33.000Z",
      "fileName": "triggers/FSL__CalculateTravelTimeOnServiceChange.trigger",
      "fullName": "FSL__CalculateTravelTimeOnServiceChange",
      "id": "01q1I000000oclQQAQ",
      "lastModifiedById": "0051I000000cjG8QAI",
      "lastModifiedByName": "FSL",
      "lastModifiedDate": "2019-10-13T03:20:40.000Z",
      "manageableState": "installed",
      "namespacePrefix": "FSL",
      "type": "ApexTrigger"
    },
    {
      "createdById": "0051I000000lrUiQAI",
      "createdByName": "Pardot",
      "createdDate": "2018-03-28T02:18:04.000Z",
      "fileName": "triggers/pi__CampaignDeleteCheck.trigger",
      "fullName": "pi__CampaignDeleteCheck",
      "id": "01q1I000001cwcbQAA",
      "lastModifiedById": "0051I000000lrUiQAI",
      "lastModifiedByName": "Pardot",
      "lastModifiedDate": "2018-03-28T02:18:04.000Z",
      "manageableState": "installed",
      "namespacePrefix": "pi",
      "type": "ApexTrigger"
    },
    {
      "createdById": "0051I000000npTMQAY",
      "createdByName": "Peerless Admin",
      "createdDate": "2019-10-10T06:59:12.000Z",
      "fileName": "triggers/APXTConga4__ReassignWhatId2.trigger",
      "fullName": "APXTConga4__ReassignWhatId2",
      "id": "01q17000000QAYuAAO",
      "lastModifiedById": "0051I000000npTMQAY",
      "lastModifiedByName": "Peerless Admin",
      "lastModifiedDate": "2019-10-10T06:59:12.000Z",
      "manageableState": "installed",
      "namespacePrefix": "APXTConga4",
      "type": "ApexTrigger"
    },
    {
      "createdById": "0051I000000cWGjQAM",
      "createdByName": "Dean White",
      "createdDate": "2017-09-22T04:06:33.000Z",
      "fileName": "triggers/FSL__TR0023_ServiceTerritory_BeforeAfterUpdate.trigger",
      "fullName": "FSL__TR0023_ServiceTerritory_BeforeAfterUpdate",
      "id": "01q1I000000oclaQAA",
      "lastModifiedById": "0051I000000cjG8QAI",
      "lastModifiedByName": "FSL",
      "lastModifiedDate": "2019-10-13T03:20:41.000Z",
      "manageableState": "installed",
      "namespacePrefix": "FSL",
      "type": "ApexTrigger"
    },
    {
      "createdById": "0051I000000cjG8QAI",
      "createdByName": "FSL",
      "createdDate": "2018-06-09T07:20:25.000Z",
      "fileName": "triggers/FSL__TR013_OptimizationRequestBeforeInsert.trigger",
      "fullName": "FSL__TR013_OptimizationRequestBeforeInsert",
      "id": "01q1I000000C7RiQAK",
      "lastModifiedById": "0051I000000cjG8QAI",
      "lastModifiedByName": "FSL",
      "lastModifiedDate": "2019-10-13T03:20:42.000Z",
      "manageableState": "installed",
      "namespacePrefix": "FSL",
      "type": "ApexTrigger"
    },
    {
      "createdById": "0051I000002SKdRQAW",
      "createdByName": "MapAnything",
      "createdDate": "2019-02-24T17:25:19.000Z",
      "fileName": "triggers/sma__MATerritory.trigger",
      "fullName": "sma__MATerritory",
      "id": "01q1I000001ZHRyQAO",
      "lastModifiedById": "0051I000002SKdRQAW",
      "lastModifiedByName": "MapAnything",
      "lastModifiedDate": "2019-11-15T06:31:43.000Z",
      "manageableState": "installed",
      "namespacePrefix": "sma",
      "type": "ApexTrigger"
    },
    {
      "createdById": "0051I000000cWGjQAM",
      "createdByName": "Dean White",
      "createdDate": "2017-09-22T04:06:33.000Z",
      "fileName": "triggers/FSL__TR007_ResourceAbsence_BeforeDelete.trigger",
      "fullName": "FSL__TR007_ResourceAbsence_BeforeDelete",
      "id": "01q1I000000ocloQAA",
      "lastModifiedById": "0051I000000cjG8QAI",
      "lastModifiedByName": "FSL",
      "lastModifiedDate": "2019-10-13T03:20:42.000Z",
      "manageableState": "installed",
      "namespacePrefix": "FSL",
      "type": "ApexTrigger"
    },
    {
      "createdById": "0051I000000cWGjQAM",
      "createdByName": "Dean White",
      "createdDate": "2017-10-22T07:01:36.000Z",
      "fileName": "triggers/EmployeeProfileImageHandler.trigger",
      "fullName": "EmployeeProfileImageHandler",
      "id": "01q1I000000QBEGQA4",
      "lastModifiedById": "0051I000000npTMQAY",
      "lastModifiedByName": "Peerless Admin",
      "lastModifiedDate": "2019-07-02T17:22:55.000Z",
      "manageableState": "unmanaged",
      "type": "ApexTrigger"
    },
    {
      "createdById": "0051I000000cWGjQAM",
      "createdByName": "Dean White",
      "createdDate": "2017-09-22T04:06:33.000Z",
      "fileName": "triggers/FSL__TR001_Service_AfterUpdate.trigger",
      "fullName": "FSL__TR001_Service_AfterUpdate",
      "id": "01q1I000000oclVQAQ",
      "lastModifiedById": "0051I000000cjG8QAI",
      "lastModifiedByName": "FSL",
      "lastModifiedDate": "2019-10-13T03:20:41.000Z",
      "manageableState": "installed",
      "namespacePrefix": "FSL",
      "type": "ApexTrigger"
    },
    {
      "createdById": "0051I000000npTMQAY",
      "createdByName": "Peerless Admin",
      "createdDate": "2019-06-20T00:43:41.000Z",
      "fileName": "triggers/InstallationTerritory.trigger",
      "fullName": "InstallationTerritory",
      "id": "01q17000000BGtOAAW",
      "lastModifiedById": "0051I000000npTMQAY",
      "lastModifiedByName": "Peerless Admin",
      "lastModifiedDate": "2019-06-20T01:34:14.000Z",
      "manageableState": "unmanaged",
      "type": "ApexTrigger"
    },
    {
      "createdById": "0051I000000npTMQAY",
      "createdByName": "Peerless Admin",
      "createdDate": "2018-02-20T16:45:09.000Z",
      "fileName": "triggers/dsfs__ConnectRecipientToDocuSignStatus.trigger",
      "fullName": "dsfs__ConnectRecipientToDocuSignStatus",
      "id": "01q1I000000SqfHQAS",
      "lastModifiedById": "0051I000000npTMQAY",
      "lastModifiedByName": "Peerless Admin",
      "lastModifiedDate": "2018-02-20T16:45:09.000Z",
      "manageableState": "installed",
      "namespacePrefix": "dsfs",
      "type": "ApexTrigger"
    },
    {
      "createdById": "0051I000000cjG8QAI",
      "createdByName": "FSL",
      "createdDate": "2017-10-14T07:02:33.000Z",
      "fileName": "triggers/FSL__TR051_TimeDependency_After_Insert.trigger",
      "fullName": "FSL__TR051_TimeDependency_After_Insert",
      "id": "01q1I000000PqstQAC",
      "lastModifiedById": "0051I000000cjG8QAI",
      "lastModifiedByName": "FSL",
      "lastModifiedDate": "2019-10-13T03:20:44.000Z",
      "manageableState": "installed",
      "namespacePrefix": "FSL",
      "type": "ApexTrigger"
    },
    {
      "createdById": "0051I000000cWGjQAM",
      "createdByName": "Dean White",
      "createdDate": "2017-09-22T04:06:34.000Z",
      "fileName": "triggers/FSL__TR021_AssignedResource_BeforeInsert.trigger",
      "fullName": "FSL__TR021_AssignedResource_BeforeInsert",
      "id": "01q1I000000ocm6QAA",
      "lastModifiedById": "0051I000000cjG8QAI",
      "lastModifiedByName": "FSL",
      "lastModifiedDate": "2019-10-13T03:20:43.000Z",
      "manageableState": "installed",
      "namespacePrefix": "FSL",
      "type": "ApexTrigger"
    },
    {
      "createdById": "0051I000000cWGjQAM",
      "createdByName": "Dean White",
      "createdDate": "2017-09-22T04:06:34.000Z",
      "fileName": "triggers/FSL__TR021_AssignedResource_BeforeDelete.trigger",
      "fullName": "FSL__TR021_AssignedResource_BeforeDelete",
      "id": "01q1I000000ocm5QAA",
      "lastModifiedById": "0051I000000cjG8QAI",
      "lastModifiedByName": "FSL",
      "lastModifiedDate": "2019-10-13T03:20:43.000Z",
      "manageableState": "installed",
      "namespacePrefix": "FSL",
      "type": "ApexTrigger"
    },
    {
      "createdById": "0051I000000cWGjQAM",
      "createdByName": "Dean White",
      "createdDate": "2017-09-22T04:06:33.000Z",
      "fileName": "triggers/FSL__TR008_Resource_AfterInsert.trigger",
      "fullName": "FSL__TR008_Resource_AfterInsert",
      "id": "01q1I000000oclrQAA",
      "lastModifiedById": "0051I000000cjG8QAI",
      "lastModifiedByName": "FSL",
      "lastModifiedDate": "2019-10-13T03:20:42.000Z",
      "manageableState": "installed",
      "namespacePrefix": "FSL",
      "type": "ApexTrigger"
    },
    {
      "createdById": "0051I000000cWGjQAM",
      "createdByName": "Dean White",
      "createdDate": "2017-09-22T04:06:34.000Z",
      "fileName": "triggers/FSL__TR026_WorkRule_BeforeDelete.trigger",
      "fullName": "FSL__TR026_WorkRule_BeforeDelete",
      "id": "01q1I000000ocmKQAQ",
      "lastModifiedById": "0051I000000cjG8QAI",
      "lastModifiedByName": "FSL",
      "lastModifiedDate": "2019-10-13T03:20:44.000Z",
      "manageableState": "installed",
      "namespacePrefix": "FSL",
      "type": "ApexTrigger"
    },
    {
      "createdById": "0051I000000cjG8QAI",
      "createdByName": "FSL",
      "createdDate": "2018-02-12T15:09:25.000Z",
      "fileName": "triggers/FSL__TR008_ServiceResource_BeforeInsert.trigger",
      "fullName": "FSL__TR008_ServiceResource_BeforeInsert",
      "id": "01q1I000000So5IQAS",
      "lastModifiedById": "0051I000000cjG8QAI",
      "lastModifiedByName": "FSL",
      "lastModifiedDate": "2019-10-13T03:20:42.000Z",
      "manageableState": "installed",
      "namespacePrefix": "FSL",
      "type": "ApexTrigger"
    },
    {
      "createdById": "0051I000000cWGjQAM",
      "createdByName": "Dean White",
      "createdDate": "2017-09-22T04:06:33.000Z",
      "fileName": "triggers/FSL__TR020_ResourceTerritories_BeforeDelete.trigger",
      "fullName": "FSL__TR020_ResourceTerritories_BeforeDelete",
      "id": "01q1I000000oclzQAA",
      "lastModifiedById": "0051I000000cjG8QAI",
      "lastModifiedByName": "FSL",
      "lastModifiedDate": "2019-10-13T03:20:42.000Z",
      "manageableState": "installed",
      "namespacePrefix": "FSL",
      "type": "ApexTrigger"
    },
    {
      "createdById": "0051I000000cjG8QAI",
      "createdByName": "FSL",
      "createdDate": "2018-06-09T07:20:25.000Z",
      "fileName": "triggers/FSL__TR010_SchedulingPolicy_BeforeInsertUpdate.trigger",
      "fullName": "FSL__TR010_SchedulingPolicy_BeforeInsertUpdate",
      "id": "01q1I000000C7RhQAK",
      "lastModifiedById": "0051I000000cjG8QAI",
      "lastModifiedByName": "FSL",
      "lastModifiedDate": "2019-10-13T03:20:42.000Z",
      "manageableState": "installed",
      "namespacePrefix": "FSL",
      "type": "ApexTrigger"
    },
    {
      "createdById": "0051I000000cjG8QAI",
      "createdByName": "FSL",
      "createdDate": "2017-10-14T07:02:33.000Z",
      "fileName": "triggers/FSL__TR051_TimeDependency_Before_Update.trigger",
      "fullName": "FSL__TR051_TimeDependency_Before_Update",
      "id": "01q1I000000PqsuQAC",
      "lastModifiedById": "0051I000000cjG8QAI",
      "lastModifiedByName": "FSL",
      "lastModifiedDate": "2019-10-13T03:20:44.000Z",
      "manageableState": "installed",
      "namespacePrefix": "FSL",
      "type": "ApexTrigger"
    },
    {
      "createdById": "0051I000000cWGjQAM",
      "createdByName": "Dean White",
      "createdDate": "2017-09-22T04:06:34.000Z",
      "fileName": "triggers/FSL__TR022_WorkOrderLineItem_AfterInsert.trigger",
      "fullName": "FSL__TR022_WorkOrderLineItem_AfterInsert",
      "id": "01q1I000000ocm8QAA",
      "lastModifiedById": "0051I000000cjG8QAI",
      "lastModifiedByName": "FSL",
      "lastModifiedDate": "2019-10-13T03:20:43.000Z",
      "manageableState": "installed",
      "namespacePrefix": "FSL",
      "type": "ApexTrigger"
    },
    {
      "createdById": "0051I000000npTMQAY",
      "createdByName": "Peerless Admin",
      "createdDate": "2018-02-20T16:45:09.000Z",
      "fileName": "triggers/dsfs__DocuSignChatterAttachmentTrigger.trigger",
      "fullName": "dsfs__DocuSignChatterAttachmentTrigger",
      "id": "01q1I000000SqfIQAS",
      "lastModifiedById": "0051I000000npTMQAY",
      "lastModifiedByName": "Peerless Admin",
      "lastModifiedDate": "2018-02-20T16:45:09.000Z",
      "manageableState": "installed",
      "namespacePrefix": "dsfs",
      "type": "ApexTrigger"
    },
    {
      "createdById": "0051I000000cjG8QAI",
      "createdByName": "FSL",
      "createdDate": "2018-02-12T15:09:24.000Z",
      "fileName": "triggers/FSL__TR0013_ServiceCrewMember_BeforeUpdate.trigger",
      "fullName": "FSL__TR0013_ServiceCrewMember_BeforeUpdate",
      "id": "01q1I000000So5HQAS",
      "lastModifiedById": "0051I000000cjG8QAI",
      "lastModifiedByName": "FSL",
      "lastModifiedDate": "2019-10-13T03:20:41.000Z",
      "manageableState": "installed",
      "namespacePrefix": "FSL",
      "type": "ApexTrigger"
    },
    {
      "createdById": "0051I000002SKdRQAW",
      "createdByName": "MapAnything",
      "createdDate": "2019-02-24T17:25:19.000Z",
      "fileName": "triggers/sma__MALayer.trigger",
      "fullName": "sma__MALayer",
      "id": "01q1I000001ZHRxQAO",
      "lastModifiedById": "0051I000002SKdRQAW",
      "lastModifiedByName": "MapAnything",
      "lastModifiedDate": "2019-11-15T06:31:43.000Z",
      "manageableState": "installed",
      "namespacePrefix": "sma",
      "type": "ApexTrigger"
    },
    {
      "createdById": "0051I000000npTMQAY",
      "createdByName": "Peerless Admin",
      "createdDate": "2019-04-08T14:42:02.000Z",
      "fileName": "triggers/rh2__PS_Rollup_Dummy.trigger",
      "fullName": "rh2__PS_Rollup_Dummy",
      "id": "01q1I000001ZItXQAW",
      "lastModifiedById": "0051I000000npTMQAY",
      "lastModifiedByName": "Peerless Admin",
      "lastModifiedDate": "2019-04-08T14:42:02.000Z",
      "manageableState": "installed",
      "namespacePrefix": "rh2",
      "type": "ApexTrigger"
    },
    {
      "createdById": "0051I000000cWGjQAM",
      "createdByName": "Dean White",
      "createdDate": "2017-09-22T04:06:33.000Z",
      "fileName": "triggers/FSL__TR005_UserTerritory_AfterDelete.trigger",
      "fullName": "FSL__TR005_UserTerritory_AfterDelete",
      "id": "01q1I000000oclgQAA",
      "lastModifiedById": "0051I000000cjG8QAI",
      "lastModifiedByName": "FSL",
      "lastModifiedDate": "2019-10-13T03:20:41.000Z",
      "manageableState": "installed",
      "namespacePrefix": "FSL",
      "type": "ApexTrigger"
    },
    {
      "createdById": "0051I000000cWGjQAM",
      "createdByName": "Dean White",
      "createdDate": "2017-09-22T04:06:33.000Z",
      "fileName": "triggers/FSL__CheckDuplicationOnWorkRulesPerPolicy.trigger",
      "fullName": "FSL__CheckDuplicationOnWorkRulesPerPolicy",
      "id": "01q1I000000oclRQAQ",
      "lastModifiedById": "0051I000000cjG8QAI",
      "lastModifiedByName": "FSL",
      "lastModifiedDate": "2019-10-13T03:20:40.000Z",
      "manageableState": "installed",
      "namespacePrefix": "FSL",
      "type": "ApexTrigger"
    },
    {
      "createdById": "0051I000000npTMQAY",
      "createdByName": "Peerless Admin",
      "createdDate": "2019-04-08T15:06:56.000Z",
      "fileName": "triggers/RHX_Commission.trigger",
      "fullName": "RHX_Commission",
      "id": "01q1I000001ZIteQAG",
      "lastModifiedById": "0051I000000npTMQAY",
      "lastModifiedByName": "Peerless Admin",
      "lastModifiedDate": "2019-04-08T15:16:02.000Z",
      "manageableState": "unmanaged",
      "type": "ApexTrigger"
    },
    {
      "createdById": "0051I000000cWGjQAM",
      "createdByName": "Dean White",
      "createdDate": "2017-10-25T01:00:29.000Z",
      "fileName": "triggers/pi__LogLeadChange.trigger",
      "fullName": "pi__LogLeadChange",
      "id": "01q1I000000QHwLQAW",
      "lastModifiedById": "0051I000000cWGjQAM",
      "lastModifiedByName": "Dean White",
      "lastModifiedDate": "2017-10-25T01:00:29.000Z",
      "manageableState": "installed",
      "namespacePrefix": "pi",
      "type": "ApexTrigger"
    },
    {
      "createdById": "0051I000000cWGjQAM",
      "createdByName": "Dean White",
      "createdDate": "2017-09-22T04:06:33.000Z",
      "fileName": "triggers/FSL__TR007_ResourceAbsence_AfterInsert.trigger",
      "fullName": "FSL__TR007_ResourceAbsence_AfterInsert",
      "id": "01q1I000000oclmQAA",
      "lastModifiedById": "0051I000000cjG8QAI",
      "lastModifiedByName": "FSL",
      "lastModifiedDate": "2019-10-13T03:20:42.000Z",
      "manageableState": "installed",
      "namespacePrefix": "FSL",
      "type": "ApexTrigger"
    },
    {
      "createdById": "0051I000000cWGjQAM",
      "createdByName": "Dean White",
      "createdDate": "2017-09-22T04:06:33.000Z",
      "fileName": "triggers/FSL__TR020_ResourceTerritories_BeforeUpdate.trigger",
      "fullName": "FSL__TR020_ResourceTerritories_BeforeUpdate",
      "id": "01q1I000000ocm1QAA",
      "lastModifiedById": "0051I000000cjG8QAI",
      "lastModifiedByName": "FSL",
      "lastModifiedDate": "2019-10-13T03:20:43.000Z",
      "manageableState": "installed",
      "namespacePrefix": "FSL",
      "type": "ApexTrigger"
    },
    {
      "createdById": "0051I000000npTMQAY",
      "createdByName": "Peerless Admin",
      "createdDate": "2018-07-19T15:39:28.000Z",
      "fileName": "triggers/WorkOrderTrigger.trigger",
      "fullName": "WorkOrderTrigger",
      "id": "01q1I000000C9ioQAC",
      "lastModifiedById": "0051I000000npTMQAY",
      "lastModifiedByName": "Peerless Admin",
      "lastModifiedDate": "2018-07-19T15:39:28.000Z",
      "manageableState": "unmanaged",
      "type": "ApexTrigger"
    },
    {
      "createdById": "0051I000000cWGjQAM",
      "createdByName": "Dean White",
      "createdDate": "2017-09-22T04:06:33.000Z",
      "fileName": "triggers/FSL__TR020_ResourceTerritories_AfterInsert.trigger",
      "fullName": "FSL__TR020_ResourceTerritories_AfterInsert",
      "id": "01q1I000000oclyQAA",
      "lastModifiedById": "0051I000000cjG8QAI",
      "lastModifiedByName": "FSL",
      "lastModifiedDate": "2019-10-13T03:20:42.000Z",
      "manageableState": "installed",
      "namespacePrefix": "FSL",
      "type": "ApexTrigger"
    },
    {
      "createdById": "0051I000000npTMQAY",
      "createdByName": "Peerless Admin",
      "createdDate": "2019-08-09T01:50:34.000Z",
      "fileName": "triggers/AssignedResourceServiceAppTrigger.trigger",
      "fullName": "AssignedResourceServiceAppTrigger",
      "id": "01q17000000BoeUAAS",
      "lastModifiedById": "0051I000000npTMQAY",
      "lastModifiedByName": "Peerless Admin",
      "lastModifiedDate": "2019-08-09T05:33:15.000Z",
      "manageableState": "unmanaged",
      "type": "ApexTrigger"
    },
    {
      "createdById": "0051I000000cWGjQAM",
      "createdByName": "Dean White",
      "createdDate": "2017-09-22T04:06:33.000Z",
      "fileName": "triggers/FSL__TR005_UserTerritory_AfterUpdate.trigger",
      "fullName": "FSL__TR005_UserTerritory_AfterUpdate",
      "id": "01q1I000000ocliQAA",
      "lastModifiedById": "0051I000000cjG8QAI",
      "lastModifiedByName": "FSL",
      "lastModifiedDate": "2019-10-13T03:20:42.000Z",
      "manageableState": "installed",
      "namespacePrefix": "FSL",
      "type": "ApexTrigger"
    },
    {
      "createdById": "0051I000000cWGjQAM",
      "createdByName": "Dean White",
      "createdDate": "2017-09-22T04:06:33.000Z",
      "fileName": "triggers/FSL__TR007_ResourceAbsence_BeforeInsert.trigger",
      "fullName": "FSL__TR007_ResourceAbsence_BeforeInsert",
      "id": "01q1I000000oclpQAA",
      "lastModifiedById": "0051I000000cjG8QAI",
      "lastModifiedByName": "FSL",
      "lastModifiedDate": "2019-10-13T03:20:42.000Z",
      "manageableState": "installed",
      "namespacePrefix": "FSL",
      "type": "ApexTrigger"
    },
    {
      "createdById": "0051I000000cWGjQAM",
      "createdByName": "Dean White",
      "createdDate": "2017-09-22T04:06:33.000Z",
      "fileName": "triggers/FSL__AbsenceCalculateTravelTime.trigger",
      "fullName": "FSL__AbsenceCalculateTravelTime",
      "id": "01q1I000000oclPQAQ",
      "lastModifiedById": "0051I000000cjG8QAI",
      "lastModifiedByName": "FSL",
      "lastModifiedDate": "2019-10-13T03:20:40.000Z",
      "manageableState": "installed",
      "namespacePrefix": "FSL",
      "type": "ApexTrigger"
    },
    {
      "createdById": "0051I000000cWGjQAM",
      "createdByName": "Dean White",
      "createdDate": "2017-09-22T04:06:33.000Z",
      "fileName": "triggers/FSL__TR0023_ServiceTerritory_BeforeInsert.trigger",
      "fullName": "FSL__TR0023_ServiceTerritory_BeforeInsert",
      "id": "01q1I000000oclcQAA",
      "lastModifiedById": "0051I000000cjG8QAI",
      "lastModifiedByName": "FSL",
      "lastModifiedDate": "2019-10-13T03:20:41.000Z",
      "manageableState": "installed",
      "namespacePrefix": "FSL",
      "type": "ApexTrigger"
    },
    {
      "createdById": "0051I000000cWGjQAM",
      "createdByName": "Dean White",
      "createdDate": "2017-09-22T04:06:34.000Z",
      "fileName": "triggers/FSL__TR025_ServiceResourceSkill_BeforeInsert.trigger",
      "fullName": "FSL__TR025_ServiceResourceSkill_BeforeInsert",
      "id": "01q1I000000ocmIQAQ",
      "lastModifiedById": "0051I000000cjG8QAI",
      "lastModifiedByName": "FSL",
      "lastModifiedDate": "2019-10-13T03:20:44.000Z",
      "manageableState": "installed",
      "namespacePrefix": "FSL",
      "type": "ApexTrigger"
    },
    {
      "createdById": "0051I000000npTMQAY",
      "createdByName": "Peerless Admin",
      "createdDate": "2018-07-20T22:09:31.000Z",
      "fileName": "triggers/sma__PopulateLookUpFieldsOnMAWaypoint.trigger",
      "fullName": "sma__PopulateLookUpFieldsOnMAWaypoint",
      "id": "01q1I000000C9lDQAS",
      "lastModifiedById": "0051I000002SKdRQAW",
      "lastModifiedByName": "MapAnything",
      "lastModifiedDate": "2019-11-15T06:31:43.000Z",
      "manageableState": "installed",
      "namespacePrefix": "sma",
      "type": "ApexTrigger"
    },
    {
      "createdById": "0051I000000cWGjQAM",
      "createdByName": "Dean White",
      "createdDate": "2017-09-22T04:06:33.000Z",
      "fileName": "triggers/FSL__TR001_Service_BeforeUpdate.trigger",
      "fullName": "FSL__TR001_Service_BeforeUpdate",
      "id": "01q1I000000oclYQAQ",
      "lastModifiedById": "0051I000000cjG8QAI",
      "lastModifiedByName": "FSL",
      "lastModifiedDate": "2019-10-13T03:20:41.000Z",
      "manageableState": "installed",
      "namespacePrefix": "FSL",
      "type": "ApexTrigger"
    },
    {
      "createdById": "0051I000002SKdRQAW",
      "createdByName": "MapAnything",
      "createdDate": "2019-02-24T17:25:19.000Z",
      "fileName": "triggers/sma__MATerritoryNode.trigger",
      "fullName": "sma__MATerritoryNode",
      "id": "01q1I000001ZHS1QAO",
      "lastModifiedById": "0051I000002SKdRQAW",
      "lastModifiedByName": "MapAnything",
      "lastModifiedDate": "2019-11-15T06:31:43.000Z",
      "manageableState": "installed",
      "namespacePrefix": "sma",
      "type": "ApexTrigger"
    },
    {
      "createdById": "0051I000000npTMQAY",
      "createdByName": "Peerless Admin",
      "createdDate": "2019-04-08T14:42:02.000Z",
      "fileName": "triggers/rh2__PS_RH_Job.trigger",
      "fullName": "rh2__PS_RH_Job",
      "id": "01q1I000001ZItWQAW",
      "lastModifiedById": "0051I000000npTMQAY",
      "lastModifiedByName": "Peerless Admin",
      "lastModifiedDate": "2019-04-08T14:42:02.000Z",
      "manageableState": "installed",
      "namespacePrefix": "rh2",
      "type": "ApexTrigger"
    },
    {
      "createdById": "0051I000000cWGjQAM",
      "createdByName": "Dean White",
      "createdDate": "2017-09-22T04:06:33.000Z",
      "fileName": "triggers/FSL__TR004_Event_BeforeInsert.trigger",
      "fullName": "FSL__TR004_Event_BeforeInsert",
      "id": "01q1I000000ocleQAA",
      "lastModifiedById": "0051I000000cjG8QAI",
      "lastModifiedByName": "FSL",
      "lastModifiedDate": "2019-10-13T03:20:41.000Z",
      "manageableState": "installed",
      "namespacePrefix": "FSL",
      "type": "ApexTrigger"
    },
    {
      "createdById": "0051I000000cWGjQAM",
      "createdByName": "Dean White",
      "createdDate": "2017-09-22T04:06:33.000Z",
      "fileName": "triggers/FSL__TR004_Event_BeforeUpdate.trigger",
      "fullName": "FSL__TR004_Event_BeforeUpdate",
      "id": "01q1I000000oclfQAA",
      "lastModifiedById": "0051I000000cjG8QAI",
      "lastModifiedByName": "FSL",
      "lastModifiedDate": "2019-10-13T03:20:41.000Z",
      "manageableState": "installed",
      "namespacePrefix": "FSL",
      "type": "ApexTrigger"
    },
    {
      "createdById": "0051I000000cWGjQAM",
      "createdByName": "Dean White",
      "createdDate": "2017-09-22T04:06:34.000Z",
      "fileName": "triggers/FSL__TR022_WorkOrderLineItem_BeforeUpdate.trigger",
      "fullName": "FSL__TR022_WorkOrderLineItem_BeforeUpdate",
      "id": "01q1I000000ocmBQAQ",
      "lastModifiedById": "0051I000000cjG8QAI",
      "lastModifiedByName": "FSL",
      "lastModifiedDate": "2019-10-13T03:20:43.000Z",
      "manageableState": "installed",
      "namespacePrefix": "FSL",
      "type": "ApexTrigger"
    },
    {
      "createdById": "0051I000000cjG8QAI",
      "createdByName": "FSL",
      "createdDate": "2017-10-14T07:02:33.000Z",
      "fileName": "triggers/FSL__TR034_OperatingHours_BeforeDelete.trigger",
      "fullName": "FSL__TR034_OperatingHours_BeforeDelete",
      "id": "01q1I000000PqsrQAC",
      "lastModifiedById": "0051I000000cjG8QAI",
      "lastModifiedByName": "FSL",
      "lastModifiedDate": "2019-10-13T03:20:44.000Z",
      "manageableState": "installed",
      "namespacePrefix": "FSL",
      "type": "ApexTrigger"
    },
    {
      "createdById": "0051I000000cjG8QAI",
      "createdByName": "FSL",
      "createdDate": "2017-10-14T07:02:33.000Z",
      "fileName": "triggers/FSL__TR028_PolygonBeforeInsert.trigger",
      "fullName": "FSL__TR028_PolygonBeforeInsert",
      "id": "01q1I000000PqsqQAC",
      "lastModifiedById": "0051I000000cjG8QAI",
      "lastModifiedByName": "FSL",
      "lastModifiedDate": "2019-10-13T03:20:44.000Z",
      "manageableState": "installed",
      "namespacePrefix": "FSL",
      "type": "ApexTrigger"
    },
    {
      "createdById": "0051I000000npTMQAY",
      "createdByName": "Peerless Admin",
      "createdDate": "2019-04-08T14:42:02.000Z",
      "fileName": "triggers/rh2__PS_Import_Rollups.trigger",
      "fullName": "rh2__PS_Import_Rollups",
      "id": "01q1I000001ZItUQAW",
      "lastModifiedById": "0051I000000npTMQAY",
      "lastModifiedByName": "Peerless Admin",
      "lastModifiedDate": "2019-04-08T14:42:02.000Z",
      "manageableState": "installed",
      "namespacePrefix": "rh2",
      "type": "ApexTrigger"
    },
    {
      "createdById": "0051I000000cWGjQAM",
      "createdByName": "Dean White",
      "createdDate": "2017-09-22T04:06:33.000Z",
      "fileName": "triggers/FSL__TR007_ResourceAbsence_AfterDelete.trigger",
      "fullName": "FSL__TR007_ResourceAbsence_AfterDelete",
      "id": "01q1I000000ocllQAA",
      "lastModifiedById": "0051I000000cjG8QAI",
      "lastModifiedByName": "FSL",
      "lastModifiedDate": "2019-10-13T03:20:42.000Z",
      "manageableState": "installed",
      "namespacePrefix": "FSL",
      "type": "ApexTrigger"
    },
    {
      "createdById": "0051I000000cjG8QAI",
      "createdByName": "FSL",
      "createdDate": "2017-10-14T07:02:33.000Z",
      "fileName": "triggers/FSL__TR051_TimeDependency_After_Delete.trigger",
      "fullName": "FSL__TR051_TimeDependency_After_Delete",
      "id": "01q1I000000PqssQAC",
      "lastModifiedById": "0051I000000cjG8QAI",
      "lastModifiedByName": "FSL",
      "lastModifiedDate": "2019-10-13T03:20:44.000Z",
      "manageableState": "installed",
      "namespacePrefix": "FSL",
      "type": "ApexTrigger"
    },
    {
      "createdById": "0051I000000cWGjQAM",
      "createdByName": "Dean White",
      "createdDate": "2017-09-22T04:06:33.000Z",
      "fileName": "triggers/FSL__TR0023_ServiceTerritory_BeforeDelete.trigger",
      "fullName": "FSL__TR0023_ServiceTerritory_BeforeDelete",
      "id": "01q1I000000oclbQAA",
      "lastModifiedById": "0051I000000cjG8QAI",
      "lastModifiedByName": "FSL",
      "lastModifiedDate": "2019-10-13T03:20:41.000Z",
      "manageableState": "installed",
      "namespacePrefix": "FSL",
      "type": "ApexTrigger"
    },
    {
      "createdById": "0051I000000cWGjQAM",
      "createdByName": "Dean White",
      "createdDate": "2017-09-22T04:06:33.000Z",
      "fileName": "triggers/FSL__TR013_OptimizationRequestBeforeUpdate.trigger",
      "fullName": "FSL__TR013_OptimizationRequestBeforeUpdate",
      "id": "01q1I000000oclxQAA",
      "lastModifiedById": "0051I000000cjG8QAI",
      "lastModifiedByName": "FSL",
      "lastModifiedDate": "2019-10-13T03:20:42.000Z",
      "manageableState": "installed",
      "namespacePrefix": "FSL",
      "type": "ApexTrigger"
    },
    {
      "createdById": "0051I000000cWGjQAM",
      "createdByName": "Dean White",
      "createdDate": "2017-09-22T04:06:33.000Z",
      "fileName": "triggers/FSL__TR008_ServiceResource_AfterUpdate.trigger",
      "fullName": "FSL__TR008_ServiceResource_AfterUpdate",
      "id": "01q1I000000oclsQAA",
      "lastModifiedById": "0051I000000cjG8QAI",
      "lastModifiedByName": "FSL",
      "lastModifiedDate": "2019-10-13T03:20:42.000Z",
      "manageableState": "installed",
      "namespacePrefix": "FSL",
      "type": "ApexTrigger"
    },
    {
      "createdById": "0051I000000cWGjQAM",
      "createdByName": "Dean White",
      "createdDate": "2017-09-22T04:06:33.000Z",
      "fileName": "triggers/FSL__TR005_UserTerritory_BeforeUpdate.trigger",
      "fullName": "FSL__TR005_UserTerritory_BeforeUpdate",
      "id": "01q1I000000oclkQAA",
      "lastModifiedById": "0051I000000cjG8QAI",
      "lastModifiedByName": "FSL",
      "lastModifiedDate": "2019-10-13T03:20:42.000Z",
      "manageableState": "installed",
      "namespacePrefix": "FSL",
      "type": "ApexTrigger"
    },
    {
      "createdById": "0051I000000cWGjQAM",
      "createdByName": "Dean White",
      "createdDate": "2017-09-22T04:06:34.000Z",
      "fileName": "triggers/FSL__TR025_ServiceResourceSkill_BeforeUpdate.trigger",
      "fullName": "FSL__TR025_ServiceResourceSkill_BeforeUpdate",
      "id": "01q1I000000ocmJQAQ",
      "lastModifiedById": "0051I000000cjG8QAI",
      "lastModifiedByName": "FSL",
      "lastModifiedDate": "2019-10-13T03:20:44.000Z",
      "manageableState": "installed",
      "namespacePrefix": "FSL",
      "type": "ApexTrigger"
    },
    {
      "createdById": "0051I000000npTMQAY",
      "createdByName": "Peerless Admin",
      "createdDate": "2019-04-08T14:42:02.000Z",
      "fileName": "triggers/rh2__PS_Contact_Describe_Async.trigger",
      "fullName": "rh2__PS_Contact_Describe_Async",
      "id": "01q1I000001ZItRQAW",
      "lastModifiedById": "0051I000000npTMQAY",
      "lastModifiedByName": "Peerless Admin",
      "lastModifiedDate": "2019-04-08T14:42:02.000Z",
      "manageableState": "installed",
      "namespacePrefix": "rh2",
      "type": "ApexTrigger"
    },
    {
      "createdById": "0051I000000cWGjQAM",
      "createdByName": "Dean White",
      "createdDate": "2017-09-22T04:06:33.000Z",
      "fileName": "triggers/FSL__TR020_ResourceTerritories_BeforeInsert.trigger",
      "fullName": "FSL__TR020_ResourceTerritories_BeforeInsert",
      "id": "01q1I000000ocm0QAA",
      "lastModifiedById": "0051I000000cjG8QAI",
      "lastModifiedByName": "FSL",
      "lastModifiedDate": "2019-10-13T03:20:42.000Z",
      "manageableState": "installed",
      "namespacePrefix": "FSL",
      "type": "ApexTrigger"
    },
    {
      "createdById": "0051I000000npTMQAY",
      "createdByName": "Peerless Admin",
      "createdDate": "2019-10-10T06:59:12.000Z",
      "fileName": "triggers/APXTConga4__CleanUpRecords2.trigger",
      "fullName": "APXTConga4__CleanUpRecords2",
      "id": "01q17000000QAYtAAO",
      "lastModifiedById": "0051I000000npTMQAY",
      "lastModifiedByName": "Peerless Admin",
      "lastModifiedDate": "2019-10-10T06:59:12.000Z",
      "manageableState": "installed",
      "namespacePrefix": "APXTConga4",
      "type": "ApexTrigger"
    },
    {
      "createdById": "0051I000000cWGjQAM",
      "createdByName": "Dean White",
      "createdDate": "2017-09-22T04:06:34.000Z",
      "fileName": "triggers/FSL__TR024_SkillRequirement_BeforeInsert.trigger",
      "fullName": "FSL__TR024_SkillRequirement_BeforeInsert",
      "id": "01q1I000000ocmGQAQ",
      "lastModifiedById": "0051I000000cjG8QAI",
      "lastModifiedByName": "FSL",
      "lastModifiedDate": "2019-10-13T03:20:43.000Z",
      "manageableState": "installed",
      "namespacePrefix": "FSL",
      "type": "ApexTrigger"
    },
    {
      "createdById": "0051I000000cWGjQAM",
      "createdByName": "Dean White",
      "createdDate": "2017-09-22T04:06:34.000Z",
      "fileName": "triggers/FSL__TR022_WorkOrder_BeforeUpdate.trigger",
      "fullName": "FSL__TR022_WorkOrder_BeforeUpdate",
      "id": "01q1I000000ocmFQAQ",
      "lastModifiedById": "0051I000000cjG8QAI",
      "lastModifiedByName": "FSL",
      "lastModifiedDate": "2019-10-13T03:20:43.000Z",
      "manageableState": "installed",
      "namespacePrefix": "FSL",
      "type": "ApexTrigger"
    },
    {
      "createdById": "0051I000000npTMQAY",
      "createdByName": "Peerless Admin",
      "createdDate": "2018-02-20T16:45:09.000Z",
      "fileName": "triggers/dsfs__DocuSignChatterRecipientStatusTrigger.trigger",
      "fullName": "dsfs__DocuSignChatterRecipientStatusTrigger",
      "id": "01q1I000000SqfKQAS",
      "lastModifiedById": "0051I000000npTMQAY",
      "lastModifiedByName": "Peerless Admin",
      "lastModifiedDate": "2018-02-20T16:45:09.000Z",
      "manageableState": "installed",
      "namespacePrefix": "dsfs",
      "type": "ApexTrigger"
    },
    {
      "createdById": "0051I000000cWGjQAM",
      "createdByName": "Dean White",
      "createdDate": "2017-09-22T04:06:33.000Z",
      "fileName": "triggers/FSL__CheckOperatorToFieldType.trigger",
      "fullName": "FSL__CheckOperatorToFieldType",
      "id": "01q1I000000oclSQAQ",
      "lastModifiedById": "0051I000000cjG8QAI",
      "lastModifiedByName": "FSL",
      "lastModifiedDate": "2019-10-13T03:20:40.000Z",
      "manageableState": "installed",
      "namespacePrefix": "FSL",
      "type": "ApexTrigger"
    },
    {
      "createdById": "0051I000000cWGjQAM",
      "createdByName": "Dean White",
      "createdDate": "2017-09-22T04:06:34.000Z",
      "fileName": "triggers/FSL__TR026_WorkRule_BeforeUpdate.trigger",
      "fullName": "FSL__TR026_WorkRule_BeforeUpdate",
      "id": "01q1I000000ocmLQAQ",
      "lastModifiedById": "0051I000000cjG8QAI",
      "lastModifiedByName": "FSL",
      "lastModifiedDate": "2019-10-13T03:20:44.000Z",
      "manageableState": "installed",
      "namespacePrefix": "FSL",
      "type": "ApexTrigger"
    },
    {
      "createdById": "0051I000000cWGjQAM",
      "createdByName": "Dean White",
      "createdDate": "2017-09-22T04:06:33.000Z",
      "fileName": "triggers/FSL__TR005_UserTerritory_AfterInsert.trigger",
      "fullName": "FSL__TR005_UserTerritory_AfterInsert",
      "id": "01q1I000000oclhQAA",
      "lastModifiedById": "0051I000000cjG8QAI",
      "lastModifiedByName": "FSL",
      "lastModifiedDate": "2019-10-13T03:20:41.000Z",
      "manageableState": "installed",
      "namespacePrefix": "FSL",
      "type": "ApexTrigger"
    },
    {
      "createdById": "0051I000000cWGjQAM",
      "createdByName": "Dean White",
      "createdDate": "2017-10-25T01:00:29.000Z",
      "fileName": "triggers/pi__LogContactChange.trigger",
      "fullName": "pi__LogContactChange",
      "id": "01q1I000000QHwKQAW",
      "lastModifiedById": "0051I000000cWGjQAM",
      "lastModifiedByName": "Dean White",
      "lastModifiedDate": "2017-10-25T01:00:29.000Z",
      "manageableState": "installed",
      "namespacePrefix": "pi",
      "type": "ApexTrigger"
    },
    {
      "createdById": "0051I000000cWGjQAM",
      "createdByName": "Dean White",
      "createdDate": "2017-09-22T04:06:34.000Z",
      "fileName": "triggers/FSL__TR022_WorkOrderLineItem_AfterUpdate.trigger",
      "fullName": "FSL__TR022_WorkOrderLineItem_AfterUpdate",
      "id": "01q1I000000ocm9QAA",
      "lastModifiedById": "0051I000000cjG8QAI",
      "lastModifiedByName": "FSL",
      "lastModifiedDate": "2019-10-13T03:20:43.000Z",
      "manageableState": "installed",
      "namespacePrefix": "FSL",
      "type": "ApexTrigger"
    },
    {
      "createdById": "0051I000000cWGjQAM",
      "createdByName": "Dean White",
      "createdDate": "2017-09-22T04:06:33.000Z",
      "fileName": "triggers/FSL__TR005_UserTerritory_BeforeInsert.trigger",
      "fullName": "FSL__TR005_UserTerritory_BeforeInsert",
      "id": "01q1I000000ocljQAA",
      "lastModifiedById": "0051I000000cjG8QAI",
      "lastModifiedByName": "FSL",
      "lastModifiedDate": "2019-10-13T03:20:42.000Z",
      "manageableState": "installed",
      "namespacePrefix": "FSL",
      "type": "ApexTrigger"
    },
    {
      "createdById": "0051I000000npTMQAY",
      "createdByName": "Peerless Admin",
      "createdDate": "2019-04-08T14:42:02.000Z",
      "fileName": "triggers/rh2__PS_Account.trigger",
      "fullName": "rh2__PS_Account",
      "id": "01q1I000001ZItPQAW",
      "lastModifiedById": "0051I000000npTMQAY",
      "lastModifiedByName": "Peerless Admin",
      "lastModifiedDate": "2019-04-08T14:42:02.000Z",
      "manageableState": "installed",
      "namespacePrefix": "rh2",
      "type": "ApexTrigger"
    },
    {
      "createdById": "0051I000000cjG8QAI",
      "createdByName": "FSL",
      "createdDate": "2018-06-09T07:20:26.000Z",
      "fileName": "triggers/FSL__TR029_GanttFilter_AfterUpdate.trigger",
      "fullName": "FSL__TR029_GanttFilter_AfterUpdate",
      "id": "01q1I000000C7RkQAK",
      "lastModifiedById": "0051I000000cjG8QAI",
      "lastModifiedByName": "FSL",
      "lastModifiedDate": "2019-10-13T03:20:44.000Z",
      "manageableState": "installed",
      "namespacePrefix": "FSL",
      "type": "ApexTrigger"
    },
    {
      "createdById": "0051I000000cWGjQAM",
      "createdByName": "Dean White",
      "createdDate": "2017-09-22T04:06:33.000Z",
      "fileName": "triggers/FSL__TR001_Service_BeforeDelete.trigger",
      "fullName": "FSL__TR001_Service_BeforeDelete",
      "id": "01q1I000000oclWQAQ",
      "lastModifiedById": "0051I000000cjG8QAI",
      "lastModifiedByName": "FSL",
      "lastModifiedDate": "2019-10-13T03:20:41.000Z",
      "manageableState": "installed",
      "namespacePrefix": "FSL",
      "type": "ApexTrigger"
    },
    {
      "createdById": "0051I000000cWGjQAM",
      "createdByName": "Dean White",
      "createdDate": "2017-09-22T04:06:33.000Z",
      "fileName": "triggers/FSL__TR004_Event_BeforeDelete.trigger",
      "fullName": "FSL__TR004_Event_BeforeDelete",
      "id": "01q1I000000ocldQAA",
      "lastModifiedById": "0051I000000cjG8QAI",
      "lastModifiedByName": "FSL",
      "lastModifiedDate": "2019-10-13T03:20:41.000Z",
      "manageableState": "installed",
      "namespacePrefix": "FSL",
      "type": "ApexTrigger"
    },
    {
      "createdById": "0051I000000npTMQAY",
      "createdByName": "Peerless Admin",
      "createdDate": "2019-04-08T14:42:02.000Z",
      "fileName": "triggers/rh2__PS_Task.trigger",
      "fullName": "rh2__PS_Task",
      "id": "01q1I000001ZItYQAW",
      "lastModifiedById": "0051I000000npTMQAY",
      "lastModifiedByName": "Peerless Admin",
      "lastModifiedDate": "2019-04-08T14:42:02.000Z",
      "manageableState": "installed",
      "namespacePrefix": "rh2",
      "type": "ApexTrigger"
    },
    {
      "createdById": "0051I000000cWGjQAM",
      "createdByName": "Dean White",
      "createdDate": "2017-09-22T04:06:33.000Z",
      "fileName": "triggers/FSL__TR0023_ServiceTerritory_AfterInsert.trigger",
      "fullName": "FSL__TR0023_ServiceTerritory_AfterInsert",
      "id": "01q1I000000oclZQAQ",
      "lastModifiedById": "0051I000000cjG8QAI",
      "lastModifiedByName": "FSL",
      "lastModifiedDate": "2019-10-13T03:20:41.000Z",
      "manageableState": "installed",
      "namespacePrefix": "FSL",
      "type": "ApexTrigger"
    },
    {
      "createdById": "0051I000000cjG8QAI",
      "createdByName": "FSL",
      "createdDate": "2018-02-12T15:09:24.000Z",
      "fileName": "triggers/FSL__TR0013_ServiceCrewMember_BeforeInsert.trigger",
      "fullName": "FSL__TR0013_ServiceCrewMember_BeforeInsert",
      "id": "01q1I000000So5GQAS",
      "lastModifiedById": "0051I000000cjG8QAI",
      "lastModifiedByName": "FSL",
      "lastModifiedDate": "2019-10-13T03:20:41.000Z",
      "manageableState": "installed",
      "namespacePrefix": "FSL",
      "type": "ApexTrigger"
    },
    {
      "createdById": "0051I000000npTMQAY",
      "createdByName": "Peerless Admin",
      "createdDate": "2019-04-08T14:42:02.000Z",
      "fileName": "triggers/rh2__PS_Contact.trigger",
      "fullName": "rh2__PS_Contact",
      "id": "01q1I000001ZItQQAW",
      "lastModifiedById": "0051I000000npTMQAY",
      "lastModifiedByName": "Peerless Admin",
      "lastModifiedDate": "2019-04-08T14:42:02.000Z",
      "manageableState": "installed",
      "namespacePrefix": "rh2",
      "type": "ApexTrigger"
    },
    {
      "createdById": "0051I000000cWGjQAM",
      "createdByName": "Dean White",
      "createdDate": "2017-09-22T04:06:34.000Z",
      "fileName": "triggers/FSL__TR022_WorkOrder_AfterInsert.trigger",
      "fullName": "FSL__TR022_WorkOrder_AfterInsert",
      "id": "01q1I000000ocmCQAQ",
      "lastModifiedById": "0051I000000cjG8QAI",
      "lastModifiedByName": "FSL",
      "lastModifiedDate": "2019-10-13T03:20:43.000Z",
      "manageableState": "installed",
      "namespacePrefix": "FSL",
      "type": "ApexTrigger"
    },
    {
      "createdById": "0051I000000npTMQAY",
      "createdByName": "Peerless Admin",
      "createdDate": "2018-12-03T15:02:23.000Z",
      "fileName": "triggers/OpportunityTerritoryTrigger.trigger",
      "fullName": "OpportunityTerritoryTrigger",
      "id": "01q1I000001IcSfQAK",
      "lastModifiedById": "0051I000000npTMQAY",
      "lastModifiedByName": "Peerless Admin",
      "lastModifiedDate": "2019-08-30T03:11:40.000Z",
      "manageableState": "unmanaged",
      "type": "ApexTrigger"
    },
    {
      "createdById": "0051I000000npTMQAY",
      "createdByName": "Peerless Admin",
      "createdDate": "2019-07-25T22:56:30.000Z",
      "fileName": "triggers/ProjectTrigger.trigger",
      "fullName": "ProjectTrigger",
      "id": "01q17000000Be1RAAS",
      "lastModifiedById": "0051I000000npTMQAY",
      "lastModifiedByName": "Peerless Admin",
      "lastModifiedDate": "2020-01-28T21:37:46.000Z",
      "manageableState": "unmanaged",
      "type": "ApexTrigger"
    },
    {
      "createdById": "0051I000000npTMQAY",
      "createdByName": "Peerless Admin",
      "createdDate": "2018-02-13T00:59:29.000Z",
      "fileName": "triggers/BudgetHandler.trigger",
      "fullName": "BudgetHandler",
      "id": "01q1I000000SoDjQAK",
      "lastModifiedById": "0051I000000npTMQAY",
      "lastModifiedByName": "Peerless Admin",
      "lastModifiedDate": "2018-02-13T00:59:29.000Z",
      "manageableState": "unmanaged",
      "type": "ApexTrigger"
    },
    {
      "createdById": "0051I000000cWGjQAM",
      "createdByName": "Dean White",
      "createdDate": "2017-09-22T04:06:34.000Z",
      "fileName": "triggers/FSL__TR021_AssignedResource_BeforeUpdate.trigger",
      "fullName": "FSL__TR021_AssignedResource_BeforeUpdate",
      "id": "01q1I000000ocm7QAA",
      "lastModifiedById": "0051I000000cjG8QAI",
      "lastModifiedByName": "FSL",
      "lastModifiedDate": "2019-10-13T03:20:43.000Z",
      "manageableState": "installed",
      "namespacePrefix": "FSL",
      "type": "ApexTrigger"
    },
    {
      "createdById": "0051I000000npTMQAY",
      "createdByName": "Peerless Admin",
      "createdDate": "2019-04-08T14:42:02.000Z",
      "fileName": "triggers/rh2__PS_Event.trigger",
      "fullName": "rh2__PS_Event",
      "id": "01q1I000001ZItTQAW",
      "lastModifiedById": "0051I000000npTMQAY",
      "lastModifiedByName": "Peerless Admin",
      "lastModifiedDate": "2019-04-08T14:42:02.000Z",
      "manageableState": "installed",
      "namespacePrefix": "rh2",
      "type": "ApexTrigger"
    },
    {
      "createdById": "0051I000000cWGjQAM",
      "createdByName": "Dean White",
      "createdDate": "2017-09-22T04:06:33.000Z",
      "fileName": "triggers/FSL__TR001_Service_BeforeInsert.trigger",
      "fullName": "FSL__TR001_Service_BeforeInsert",
      "id": "01q1I000000oclXQAQ",
      "lastModifiedById": "0051I000000cjG8QAI",
      "lastModifiedByName": "FSL",
      "lastModifiedDate": "2019-10-13T03:20:41.000Z",
      "manageableState": "installed",
      "namespacePrefix": "FSL",
      "type": "ApexTrigger"
    },
    {
      "createdById": "0051I000000cWGjQAM",
      "createdByName": "Dean White",
      "createdDate": "2017-09-22T04:06:34.000Z",
      "fileName": "triggers/FSL__TR022_WorkOrder_BeforeInsert.trigger",
      "fullName": "FSL__TR022_WorkOrder_BeforeInsert",
      "id": "01q1I000000ocmEQAQ",
      "lastModifiedById": "0051I000000cjG8QAI",
      "lastModifiedByName": "FSL",
      "lastModifiedDate": "2019-10-13T03:20:43.000Z",
      "manageableState": "installed",
      "namespacePrefix": "FSL",
      "type": "ApexTrigger"
    },
    {
      "createdById": "0051I000000cWGjQAM",
      "createdByName": "Dean White",
      "createdDate": "2017-09-22T04:06:33.000Z",
      "fileName": "triggers/FSL__TR008_ServiceResource_BeforeUpdate.trigger",
      "fullName": "FSL__TR008_ServiceResource_BeforeUpdate",
      "id": "01q1I000000ocltQAA",
      "lastModifiedById": "0051I000000cjG8QAI",
      "lastModifiedByName": "FSL",
      "lastModifiedDate": "2019-10-13T03:20:42.000Z",
      "manageableState": "installed",
      "namespacePrefix": "FSL",
      "type": "ApexTrigger"
    },
    {
      "createdById": "0051I000000cWGjQAM",
      "createdByName": "Dean White",
      "createdDate": "2017-09-22T04:06:34.000Z",
      "fileName": "triggers/FSL__TR022_WorkOrder_AfterUpdate.trigger",
      "fullName": "FSL__TR022_WorkOrder_AfterUpdate",
      "id": "01q1I000000ocmDQAQ",
      "lastModifiedById": "0051I000000cjG8QAI",
      "lastModifiedByName": "FSL",
      "lastModifiedDate": "2019-10-13T03:20:43.000Z",
      "manageableState": "installed",
      "namespacePrefix": "FSL",
      "type": "ApexTrigger"
    },
    {
      "createdById": "0051I000000npTMQAY",
      "createdByName": "Peerless Admin",
      "createdDate": "2018-12-10T18:01:14.000Z",
      "fileName": "triggers/AddPeriodStartEndDate.trigger",
      "fullName": "AddPeriodStartEndDate",
      "id": "01q1I000001IcaoQAC",
      "lastModifiedById": "0051I000000npTMQAY",
      "lastModifiedByName": "Peerless Admin",
      "lastModifiedDate": "2018-12-10T18:01:14.000Z",
      "manageableState": "unmanaged",
      "type": "ApexTrigger"
    },
    {
      "createdById": "0051I000000cWGjQAM",
      "createdByName": "Dean White",
      "createdDate": "2017-10-25T01:00:29.000Z",
      "fileName": "triggers/pi__ChangeTaskFromPardotTask.trigger",
      "fullName": "pi__ChangeTaskFromPardotTask",
      "id": "01q1I000000QHwIQAW",
      "lastModifiedById": "0051I000000cWGjQAM",
      "lastModifiedByName": "Dean White",
      "lastModifiedDate": "2017-10-25T01:00:29.000Z",
      "manageableState": "installed",
      "namespacePrefix": "pi",
      "type": "ApexTrigger"
    },
    {
      "createdById": "0051I000000npTMQAY",
      "createdByName": "Peerless Admin",
      "createdDate": "2019-08-22T01:21:07.000Z",
      "fileName": "triggers/LeadTrigger.trigger",
      "fullName": "LeadTrigger",
      "id": "01q17000000BzWfAAK",
      "lastModifiedById": "0051I000000npTMQAY",
      "lastModifiedByName": "Peerless Admin",
      "lastModifiedDate": "2019-08-22T20:58:31.000Z",
      "manageableState": "unmanaged",
      "type": "ApexTrigger"
    },
    {
      "createdById": "0051I000000npTMQAY",
      "createdByName": "Peerless Admin",
      "createdDate": "2019-08-05T23:11:28.000Z",
      "fileName": "triggers/AssignedResourceTrigger.trigger",
      "fullName": "AssignedResourceTrigger",
      "id": "01q17000000BlUSAA0",
      "lastModifiedById": "0051I000000npTMQAY",
      "lastModifiedByName": "Peerless Admin",
      "lastModifiedDate": "2019-08-10T02:42:12.000Z",
      "manageableState": "unmanaged",
      "type": "ApexTrigger"
    },
    {
      "createdById": "0051I000000cjG8QAI",
      "createdByName": "FSL",
      "createdDate": "2018-06-09T07:20:25.000Z",
      "fileName": "triggers/FSL__TR029_GanttFilter_AfterInsert.trigger",
      "fullName": "FSL__TR029_GanttFilter_AfterInsert",
      "id": "01q1I000000C7RjQAK",
      "lastModifiedById": "0051I000000cjG8QAI",
      "lastModifiedByName": "FSL",
      "lastModifiedDate": "2019-10-13T03:20:44.000Z",
      "manageableState": "installed",
      "namespacePrefix": "FSL",
      "type": "ApexTrigger"
    },
    {
      "createdById": "0051I000000npTMQAY",
      "createdByName": "Peerless Admin",
      "createdDate": "2019-08-07T19:40:43.000Z",
      "fileName": "triggers/ComplaintProjectTrigger.trigger",
      "fullName": "ComplaintProjectTrigger",
      "id": "01q17000000Bn9kAAC",
      "lastModifiedById": "0051I000000npTMQAY",
      "lastModifiedByName": "Peerless Admin",
      "lastModifiedDate": "2019-08-07T19:40:43.000Z",
      "manageableState": "unmanaged",
      "type": "ApexTrigger"
    },
    {
      "createdById": "0051I000000cWGjQAM",
      "createdByName": "Dean White",
      "createdDate": "2017-12-30T20:48:49.000Z",
      "fileName": "triggers/storeHomeDepotTrimTrigger.trigger",
      "fullName": "storeHomeDepotTrimTrigger",
      "id": "01q1I000000ScwdQAC",
      "lastModifiedById": "0051I000000npTMQAY",
      "lastModifiedByName": "Peerless Admin",
      "lastModifiedDate": "2018-04-25T20:43:00.000Z",
      "manageableState": "unmanaged",
      "type": "ApexTrigger"
    },
    {
      "createdById": "0051I000000cWGjQAM",
      "createdByName": "Dean White",
      "createdDate": "2017-09-22T04:06:33.000Z",
      "fileName": "triggers/FSL__TR010_SchedulingPolicy_BeforeDelete.trigger",
      "fullName": "FSL__TR010_SchedulingPolicy_BeforeDelete",
      "id": "01q1I000000oclvQAA",
      "lastModifiedById": "0051I000000cjG8QAI",
      "lastModifiedByName": "FSL",
      "lastModifiedDate": "2019-10-13T03:20:42.000Z",
      "manageableState": "installed",
      "namespacePrefix": "FSL",
      "type": "ApexTrigger"
    },
    {
      "createdById": "0051I000000cWGjQAM",
      "createdByName": "Dean White",
      "createdDate": "2017-10-25T01:00:29.000Z",
      "fileName": "triggers/pi__LogAccountChange.trigger",
      "fullName": "pi__LogAccountChange",
      "id": "01q1I000000QHwJQAW",
      "lastModifiedById": "0051I000000cWGjQAM",
      "lastModifiedByName": "Dean White",
      "lastModifiedDate": "2017-10-25T01:00:29.000Z",
      "manageableState": "installed",
      "namespacePrefix": "pi",
      "type": "ApexTrigger"
    },
    {
      "createdById": "0051I000000cjG8QAI",
      "createdByName": "FSL",
      "createdDate": "2018-10-13T07:13:16.000Z",
      "fileName": "triggers/FSL__TR030_GanttPalette_AfterUpdate.trigger",
      "fullName": "FSL__TR030_GanttPalette_AfterUpdate",
      "id": "01q1I000001IaalQAC",
      "lastModifiedById": "0051I000000cjG8QAI",
      "lastModifiedByName": "FSL",
      "lastModifiedDate": "2019-10-13T03:20:44.000Z",
      "manageableState": "installed",
      "namespacePrefix": "FSL",
      "type": "ApexTrigger"
    },
    {
      "createdById": "0051I000000cWGjQAM",
      "createdByName": "Dean White",
      "createdDate": "2017-09-22T04:06:33.000Z",
      "fileName": "triggers/FSL__TR007_ResourceAbsence_BeforeUpdate.trigger",
      "fullName": "FSL__TR007_ResourceAbsence_BeforeUpdate",
      "id": "01q1I000000oclqQAA",
      "lastModifiedById": "0051I000000cjG8QAI",
      "lastModifiedByName": "FSL",
      "lastModifiedDate": "2019-10-13T03:20:42.000Z",
      "manageableState": "installed",
      "namespacePrefix": "FSL",
      "type": "ApexTrigger"
    },
    {
      "createdById": "0051I000000cWGjQAM",
      "createdByName": "Dean White",
      "createdDate": "2017-09-22T04:06:34.000Z",
      "fileName": "triggers/FSL__TR022_WorkOrderLineItem_BeforeInsert.trigger",
      "fullName": "FSL__TR022_WorkOrderLineItem_BeforeInsert",
      "id": "01q1I000000ocmAQAQ",
      "lastModifiedById": "0051I000000cjG8QAI",
      "lastModifiedByName": "FSL",
      "lastModifiedDate": "2019-10-13T03:20:43.000Z",
      "manageableState": "installed",
      "namespacePrefix": "FSL",
      "type": "ApexTrigger"
    },
    {
      "createdById": "0051I000000cjG8QAI",
      "createdByName": "FSL",
      "createdDate": "2019-10-13T03:20:44.000Z",
      "fileName": "triggers/FSL__TR028_PolygonBeforeUpdate.trigger",
      "fullName": "FSL__TR028_PolygonBeforeUpdate",
      "id": "01q17000000QFgaAAG",
      "lastModifiedById": "0051I000000cjG8QAI",
      "lastModifiedByName": "FSL",
      "lastModifiedDate": "2019-10-13T03:20:44.000Z",
      "manageableState": "installed",
      "namespacePrefix": "FSL",
      "type": "ApexTrigger"
    },
    {
      "createdById": "0051I000002SKdRQAW",
      "createdByName": "MapAnything",
      "createdDate": "2019-02-24T17:25:19.000Z",
      "fileName": "triggers/sma__MATerritoryAggregationSetting.trigger",
      "fullName": "sma__MATerritoryAggregationSetting",
      "id": "01q1I000001ZHRzQAO",
      "lastModifiedById": "0051I000002SKdRQAW",
      "lastModifiedByName": "MapAnything",
      "lastModifiedDate": "2019-11-15T06:31:43.000Z",
      "manageableState": "installed",
      "namespacePrefix": "sma",
      "type": "ApexTrigger"
    }
  ]
}
